lineagex/__init__.py
lineagex/app.js
lineagex/ColumnLineage.py
lineagex/ColumnLineageNoConn.py
lineagex/example.py
lineagex/examples/dependency_example/a_table.sql
lineagex/examples/dependency_example/aa_table.sql
lineagex/examples/dependency_example/basic_patient_info.sql
lineagex/examples/dependency_example/from_aa_table.sql
lineagex/examples/dependency_example/no_dob.sql
lineagex/examples/github_example/desktop.ini
lineagex/examples/github_example/table1.sql
lineagex/examples/github_example/table2.sql
lineagex/examples/mimic-iii/code_status.sql
lineagex/examples/mimic-iii/comorbidity/elixhauser_ahrq_v37.sql
lineagex/examples/mimic-iii/comorbidity/elixhauser_ahrq_v37_no_drg.sql
lineagex/examples/mimic-iii/comorbidity/elixhauser_quan.sql
lineagex/examples/mimic-iii/comorbidity/elixhauser_score_ahrq.sql
lineagex/examples/mimic-iii/comorbidity/elixhauser_score_quan.sql
lineagex/examples/mimic-iii/demographics/heightweight.sql
lineagex/examples/mimic-iii/demographics/icustay_detail.sql
lineagex/examples/mimic-iii/demographics/icustay_hours.sql
lineagex/examples/mimic-iii/demographics/icustay_times.sql
lineagex/examples/mimic-iii/demographics/note_counts.sql
lineagex/examples/mimic-iii/demographics/weight_durations.sql
lineagex/examples/mimic-iii/diagnosis/ccs_multi_dx.csv.gz
lineagex/examples/mimic-iii/diagnosis/README.md
lineagex/examples/mimic-iii/durations/adenosine_durations.sql
lineagex/examples/mimic-iii/durations/arterial_line_durations.sql
lineagex/examples/mimic-iii/durations/central_line_durations.sql
lineagex/examples/mimic-iii/durations/crrt_durations.sql
lineagex/examples/mimic-iii/durations/dobutamine_dose.sql
lineagex/examples/mimic-iii/durations/dobutamine_durations.sql
lineagex/examples/mimic-iii/durations/dopamine_dose.sql
lineagex/examples/mimic-iii/durations/dopamine_durations.sql
lineagex/examples/mimic-iii/durations/epinephrine_dose.sql
lineagex/examples/mimic-iii/durations/epinephrine_durations.sql
lineagex-0.0.26.dist-info/METADATA
lineagex-0.0.26.dist-info/WHEEL
lineagex-0.0.26.dist-info/RECORD
