Metadata-Version: 2.1
Name: lineagex
Version: 0.0.26
Summary: A column lineage tool
License: MIT
Author: zshandy
Author-email: zshandy@gmail.com
Requires-Python: >=3.6,<4.0
Classifier: License :: OSI Approved :: MIT License
Classifier: Programming Language :: Python :: 3
Classifier: Programming Language :: Python :: 3.6
Classifier: Programming Language :: Python :: 3.7
Classifier: Programming Language :: Python :: 3.8
Classifier: Programming Language :: Python :: 3.9
Classifier: Programming Language :: Python :: 3.10
Classifier: Programming Language :: Python :: 3.11
Requires-Dist: psycopg2-binary (>=2.9.6,<3.0.0)
Requires-Dist: sqlglot (>=12.3.0,<13.0.0)
